MANIFEST.in
README.md
bottle_resource.py
requirements.txt
setup.py
tests.py
BottleResource.egg-info/PKG-INFO
BottleResource.egg-info/SOURCES.txt
BottleResource.egg-info/dependency_links.txt
BottleResource.egg-info/top_level.txt