Metadata-Version: 1.0
Name: BottleResource
Version: 0.0.1
Summary: Class based bottle endpoint resource plugin
Home-page: https://github.com/theo-l/BottleResource
Author: Liang Guisheng
Author-email: theol.liang@foxmail.com
License: UNKNOWN
Platform: UNKNOWN
